MANIFEST.in
README
setup.cfg
setup.py
config/AdK2008.etp
config/monochrome8x8.etp
config/single8x8.etp
examples/blink.py
pyetherpix/__init__.py
pyetherpix/display.py
pyetherpix/distributor.py
pyetherpix/mapping.py
pyetherpix/msg.py
pyetherpix/parse.py
pyetherpix.egg-info/PKG-INFO
pyetherpix.egg-info/SOURCES.txt
pyetherpix.egg-info/dependency_links.txt
pyetherpix.egg-info/not-zip-safe
pyetherpix.egg-info/requires.txt
pyetherpix.egg-info/top_level.txt