Metadata-Version: 1.0
Name: pyetherpix
Version: 0.3
Summary: python implementation of EtherPix output library
Home-page: https://git.blinkenarea.org?p=pyetherpix
Author: Stefan Schuermans
Author-email: stefan@schuermans.info
License: LGPLv3
Platform: UNKNOWN
